{"provides":{"IO::Socket::SSL":{"version":"1.997","file":"lib/IO/Socket/SSL.pm"},"IO::Socket::SSL::Session_Cache":{"version":"1.997","file":"lib/IO/Socket/SSL.pm"},"IO::Socket::SSL::Utils":{"version":"0.03","file":"lib/IO/Socket/SSL/Utils.pm"},"IO::Socket::SSL::OCSP_Cache":{"version":"1.997","file":"lib/IO/Socket/SSL.pm"},"IO::Socket::SSL::PublicSuffix":{"file":"lib/IO/Socket/SSL/PublicSuffix.pm"},"IO::Socket::SSL::SSL_Context":{"version":"1.997","file":"lib/IO/Socket/SSL.pm"},"IO::Socket::SSL::OCSP_Resolver":{"version":"1.997","file":"lib/IO/Socket/SSL.pm"},"IO::Socket::SSL::SSL_HANDLE":{"version":"1.997","file":"lib/IO/Socket/SSL.pm"},"IO::Socket::SSL::Intercept":{"version":"1.93","file":"lib/IO/Socket/SSL/Intercept.pm"}},"target":"IO::Socket::SSL","version":"1.997","name":"IO::Socket::SSL","dist":"IO-Socket-SSL-1.997","pathname":"S/SU/SULLR/IO-Socket-SSL-1.997.tar.gz"}